pyroll/from_dict/__init__.py
pyroll/from_dict/config.py
pyroll/from_dict/explicit_functions.py
pyroll/from_dict/from_dict.py
pyroll/from_dict/resolve.py
pyroll/from_dict/schema.py
pyroll_from_dict-3.0.0.dist-info/METADATA
pyroll_from_dict-3.0.0.dist-info/WHEEL
pyroll_from_dict-3.0.0.dist-info/licenses/LICENSE
pyroll_from_dict-3.0.0.dist-info/RECORD
